MANIFEST.in
mail_alias_view.xml
mail_followers_view.xml
mail_group_view.xml
mail_mail_view.xml
mail_message_subtype.xml
mail_message_view.xml
mail_thread_view.xml
res_config_view.xml
res_partner_view.xml
res_users_view.xml
setup.py
./__init__.py
./__openerp__.py
./mail_alias.py
./mail_followers.py
./mail_group.py
./mail_group_menu.py
./mail_mail.py
./mail_message.py
./mail_message_subtype.py
./mail_thread.py
./mail_vote.py
./res_config.py
./res_partner.py
./res_users.py
./update.py
./controllers/__init__.py
./controllers/main.py
./report/__init__.py
./tests/__init__.py
./tests/test_invite.py
./tests/test_mail_base.py
./tests/test_mail_features.py
./tests/test_mail_gateway.py
./tests/test_mail_message.py
./tests/test_message_read.py
./wizard/__init__.py
./wizard/invite.py
./wizard/mail_compose_message.py
data/mail_data.xml
data/mail_demo.xml
data/mail_group_data.xml
data/mail_group_demo_data.xml
doc/index.rst
doc/index.rst.inc
doc/mail_message.rst
doc/mail_needaction_howto.rst
doc/mail_openchatter_howto.rst
doc/mail_partner.rst
doc/mail_state.rst
doc/mail_subtype.rst
doc/mail_thread.rst
doc/tracked_field.rst
i18n/ar.po
i18n/bg.po
i18n/bs.po
i18n/ca.po
i18n/cs.po
i18n/da.po
i18n/de.po
i18n/es.po
i18n/es_CR.po
i18n/es_MX.po
i18n/es_PY.po
i18n/es_VE.po
i18n/et.po
i18n/fi.po
i18n/fr.po
i18n/gl.po
i18n/he.po
i18n/hr.po
i18n/hu.po
i18n/it.po
i18n/ja.po
i18n/ko.po
i18n/lt.po
i18n/lv.po
i18n/mail.pot
i18n/mk.po
i18n/mn.po
i18n/nl.po
i18n/pl.po
i18n/pt.po
i18n/pt_BR.po
i18n/ro.po
i18n/ru.po
i18n/sl.po
i18n/sr@latin.po
i18n/sv.po
i18n/th.po
i18n/tr.po
i18n/vi.po
i18n/zh_CN.po
i18n/zh_TW.po
images/email.jpeg
images/inbox.jpeg
images/join_a_group.jpeg
images/messages_form.jpeg
images/messages_list.jpeg
images/share_a_message.jpeg
openerp_mail.egg-info/PKG-INFO
openerp_mail.egg-info/SOURCES.txt
openerp_mail.egg-info/dependency_links.txt
openerp_mail.egg-info/requires.txt
openerp_mail.egg-info/top_level.txt
security/ir.model.access.csv
security/mail_security.xml
static/lib/jquery.expander/jquery.expander.js
static/src/img/_al.png
static/src/img/_pinky.png
static/src/img/attachment.png
static/src/img/checklist.png
static/src/img/email_icon.png
